pdf_qr_stamper-0.1.0.dist-info/METADATA
pdf_qr_stamper-0.1.0.dist-info/WHEEL
pdf_qr_stamper/__init__.py
pdf_qr_stamper/pdf_qr_stamper.pyd
pdf_qr_stamper-0.1.0.dist-info/RECORD
