Metadata-Version: 2.4
Name: pdf_qr_stamper
Version: 0.1.0
Summary: Stamp a QR code onto every page of a PDF (Rust core; Python bindings via PyO3).
License: MIT
